overdisp/__init__.py
overdisp/overdisp.py
overdisp-0.1.0.dist-info/LICENSE
overdisp-0.1.0.dist-info/METADATA
overdisp-0.1.0.dist-info/WHEEL
overdisp-0.1.0.dist-info/top_level.txt
overdisp-0.1.0.dist-info/RECORD
