Metadata-Version: 2.1
Name: overdisp
Version: 0.1.0
Summary: Estimation of overdispersion parameters
Home-page: https://github.com/anthony-aylward/overdisp.git
Author: Anthony Aylward
Author-email: aaylward@eng.ucsd.edu
License: UNKNOWN
Platform: UNKNOWN
Classifier: Programming Language :: Python :: 3
Classifier: License :: OSI Approved :: MIT License
Classifier: Operating System :: OS Independent
